qtbmodels/__init__.py
qtbmodels/_generate_names.py
qtbmodels/names.py
qtbmodels/py.typed
qtbmodels/shared.py
qtbmodels/v1/__init__.py
qtbmodels/v1/ebenhoeh2011/__init__.py
qtbmodels/v1/ebenhoeh2014/__init__.py
qtbmodels/v1/matuszynska2016npq/__init__.py
qtbmodels/v1/matuszynska2016phd/__init__.py
qtbmodels/v1/matuszynska2019/__init__.py
qtbmodels/v1/poolman2000/__init__.py
qtbmodels/v1/saadat2021/__init__.py
qtbmodels/v1/shared.py
qtbmodels/v1/utils.py
qtbmodels/v1/vanaalst2023/__init__.py
qtbmodels/v1/yokota1985/__init__.py
qtbmodels/v2/__init__.py
qtbmodels/v2/components/__init__.py
qtbmodels/v2/components/_create_imports.py
qtbmodels/v2/components/ascorbate.py
qtbmodels/v2/components/atp_adp_amp.py
qtbmodels/v2/components/co2.py
qtbmodels/v2/components/coa.py
qtbmodels/v2/components/diphosphate.py
qtbmodels/v2/components/energy.py
qtbmodels/v2/components/enzyme_factor.py
qtbmodels/v2/components/ferredoxin.py
qtbmodels/v2/components/glutamate_oxoglutarate.py
qtbmodels/v2/components/glutathion.py
qtbmodels/v2/components/hco3.py
qtbmodels/v2/components/lhc.py
qtbmodels/v2/components/nadh.py
qtbmodels/v2/components/nadph.py
qtbmodels/v2/components/nh4.py
qtbmodels/v2/components/o2.py
qtbmodels/v2/components/orthophosphate.py
qtbmodels/v2/components/pc_red.py
qtbmodels/v2/components/ph.py
qtbmodels/v2/components/pq_red.py
qtbmodels/v2/components/protons.py
qtbmodels/v2/components/psbs.py
qtbmodels/v2/components/quencher.py
qtbmodels/v2/components/readouts.py
qtbmodels/v2/components/rt.py
qtbmodels/v2/components/thioredoxin.py
qtbmodels/v2/enzymes/__init__.py
qtbmodels/v2/enzymes/_create_imports.py
qtbmodels/v2/enzymes/_utils.py
qtbmodels/v2/enzymes/a5p_isomerase.py
qtbmodels/v2/enzymes/acetoacetate_coa_ligase.py
qtbmodels/v2/enzymes/acetyl_coa_acetyltransfer.py
qtbmodels/v2/enzymes/acetyl_coa_carboxyltransfer.py
qtbmodels/v2/enzymes/aldolase_dhap_a5p_obp.py
qtbmodels/v2/enzymes/aldolase_dhap_e4p_sbp.py
qtbmodels/v2/enzymes/aldolase_dhap_gap_fbp.py
qtbmodels-0.1.0.dist-info/METADATA
qtbmodels-0.1.0.dist-info/WHEEL
qtbmodels-0.1.0.dist-info/RECORD
