Metadata-Version: 2.1
Name: qtbmodels
Version: 0.1.0
Summary: 
Author: Marvin van Aalst
Author-email: marvin.vanaalst@gmail.com
Requires-Python: >=3.11,<3.13
Classifier: Programming Language :: Python :: 3
Classifier: Programming Language :: Python :: 3.11
Classifier: Programming Language :: Python :: 3.12
Requires-Dist: modelbase (>=1.51,<2.0)
